[
    {
        "id": 1296,
        "username": "uwright",
        "email": "willie33@example.net",
        "createdOn": "01/29/2024 19:07:21",
        "comment": "Had a tough day at work but the evening at the city museum with friends made it all better.",
        "likes": 33734,
        "views": 137589
    },
    {
        "id": 1297,
        "username": "kimberly06",
        "email": "sarahcollins@example.net",
        "createdOn": "01/29/2024 21:34:26",
        "comment": "Had a lovely day at the mountain trail! The weather was perfect, and jogging was so relaxing.",
        "likes": 9199,
        "views": 7440845
    },
    {
        "id": 1298,
        "username": "gutierreztina",
        "email": "hardinglynn@example.net",
        "createdOn": "01/29/2024 16:00:47",
        "comment": "My attempt at cooking ratatouille turned out surprisingly good. Next time I'll keep practicing.",
        "likes": 12978,
        "views": 2732732
    },
    {
        "id": 1299,
        "username": "cnavarro",
        "email": "santiagokimberly@example.com",
        "createdOn": "01/29/2024 16:35:50",
        "comment": "I've been really into baking lately. Just finished a project on an organic vegetable garden. So rewarding!",
        "likes": 4379,
        "views": 6946395
    },
    {
        "id": 1300,
        "username": "powelltanya",
        "email": "wagnerterri@example.com",
        "createdOn": "01/29/2024 15:49:01",
        "comment": "Had a tough day at work but the evening at the city museum with friends made it all better.",
        "likes": 17160,
        "views": 9487125
    },
    {
        "id": 1301,
        "username": "ulewis",
        "email": "xmiller@example.com",
        "createdOn": "01/29/2024 11:21:21",
        "comment": "Just tried the new dish at The Spicy Dragon. Definitely recommend the vegan sushi platter if you love spicy flavors!",
        "likes": 14145,
        "views": 1801240
    },
    {
        "id": 1302,
        "username": "bradleyjessica",
        "email": "dcarson@example.com",
        "createdOn": "01/29/2024 18:30:54",
        "comment": "Had a tough day at work but the evening at the riverside park with friends made it all better.",
        "likes": 8329,
        "views": 4985801
    },
    {
        "id": 1303,
        "username": "poncekyle",
        "email": "mark19@example.net",
        "createdOn": "01/29/2024 17:54:33",
        "comment": "I've been really into woodworking lately. Just finished a project on a web app. So rewarding!",
        "likes": 8474,
        "views": 5367082
    },
    {
        "id": 1304,
        "username": "jpena",
        "email": "kenneth89@example.org",
        "createdOn": "01/29/2024 11:37:11",
        "comment": "Can't stop listening to Taylor Swift's new album. Easy on Me is my favorite track because it is deeply emotional.",
        "likes": 27824,
        "views": 1022809
    },
    {
        "id": 1305,
        "username": "gibbsashley",
        "email": "xkane@example.com",
        "createdOn": "01/29/2024 14:04:18",
        "comment": "Had a lovely day at the beach! The weather was perfect, and jogging was so relaxing.",
        "likes": 22541,
        "views": 6127210
    },
    {
        "id": 1306,
        "username": "jordanwalton",
        "email": "cwatkins@example.net",
        "createdOn": "01/29/2024 01:14:44",
        "comment": "Just tried the new dish at Chez Antoine. Definitely recommend the vegan sushi platter if you love sweet flavors!",
        "likes": 7666,
        "views": 8821078
    },
    {
        "id": 1307,
        "username": "ballardmichelle",
        "email": "johnthompson@example.net",
        "createdOn": "01/29/2024 18:43:44",
        "comment": "This year's SXSW was the best yet! Loved every moment of the competitions, especially the part when Jay-Z performed a surprise set.",
        "likes": 47824,
        "views": 9200622
    },
    {
        "id": 1308,
        "username": "joelbonilla",
        "email": "andrewrodriguez@example.org",
        "createdOn": "01/29/2024 04:13:28",
        "comment": "Can't believe what happened in the latest episode of Breaking Bad! Geralt of Rivia really surprised me.",
        "likes": 26662,
        "views": 6758775
    },
    {
        "id": 1309,
        "username": "zkim",
        "email": "edwin18@example.org",
        "createdOn": "01/29/2024 10:51:11",
        "comment": "Attended a workshop on yoga for beginners and it changed my perspective on is relaxing and fulfilling.",
        "likes": 26883,
        "views": 8344060
    },
    {
        "id": 1310,
        "username": "pgutierrez",
        "email": "tclark@example.com",
        "createdOn": "01/29/2024 11:51:41",
        "comment": "Read an interesting article about artificial intelligence. It's fascinating how it's a major concern for the next decade.",
        "likes": 12725,
        "views": 2194000
    },
    {
        "id": 1311,
        "username": "amanda98",
        "email": "david33@example.org",
        "createdOn": "01/29/2024 18:56:14",
        "comment": "My attempt at cooking pho turned out surprisingly good. Next time I'll adjust the baking time.",
        "likes": 36532,
        "views": 1097696
    },
    {
        "id": 1312,
        "username": "sarahstrong",
        "email": "sabrina02@example.net",
        "createdOn": "01/29/2024 07:46:37",
        "comment": "Just watched the latest NikkieTutorials video where they organized a surprise concert! Absolutely mind-blowing!",
        "likes": 22114,
        "views": 5704015
    },
    {
        "id": 1313,
        "username": "grivas",
        "email": "rlong@example.org",
        "createdOn": "01/29/2024 18:23:25",
        "comment": "This year's Coachella was the best yet! Loved every moment of the lineup, especially the part when Elon Musk gave a futuristic vision.",
        "likes": 6636,
        "views": 6661591
    },
    {
        "id": 1314,
        "username": "christophercooper",
        "email": "kellyfields@example.com",
        "createdOn": "01/29/2024 13:51:40",
        "comment": "Read an interesting article about economic policy. It's fascinating how it affects global markets.",
        "likes": 21790,
        "views": 2852957
    },
    {
        "id": 1315,
        "username": "melissabrown",
        "email": "ehanson@example.net",
        "createdOn": "01/29/2024 18:16:53",
        "comment": "Today I learned medieval history. Did you know it shaped European borders?",
        "likes": 11997,
        "views": 9124258
    },
    {
        "id": 1316,
        "username": "taylorlisa",
        "email": "perryterri@example.com",
        "createdOn": "01/29/2024 13:39:23",
        "comment": "Today I learned quantum physics. Did you know it drives consumer behavior?",
        "likes": 3370,
        "views": 7989043
    },
    {
        "id": 1317,
        "username": "luis95",
        "email": "mfox@example.net",
        "createdOn": "01/29/2024 05:14:42",
        "comment": "Had a blast at music festivals in art gallery! The crowd was delightful and the highlights were live performances.",
        "likes": 41147,
        "views": 3576681
    },
    {
        "id": 1318,
        "username": "normajohnson",
        "email": "jamesgomez@example.org",
        "createdOn": "01/29/2024 08:41:47",
        "comment": "Spent the weekend mountain biking at national park. Nature really is healing.",
        "likes": 5903,
        "views": 1326391
    },
    {
        "id": 1319,
        "username": "michaelmiles",
        "email": "michael32@example.org",
        "createdOn": "01/29/2024 21:31:54",
        "comment": "Spent the weekend camping at national park. Nature really is healing.",
        "likes": 7361,
        "views": 2953881
    },
    {
        "id": 1320,
        "username": "justinwilliams",
        "email": "xpope@example.net",
        "createdOn": "01/29/2024 14:56:30",
        "comment": "Can't believe what happened in the latest episode of Stranger Things! Jon Snow really surprised me.",
        "likes": 19026,
        "views": 9042873
    },
    {
        "id": 1321,
        "username": "awall",
        "email": "timothybryant@example.org",
        "createdOn": "01/29/2024 18:14:47",
        "comment": "If you're ever in Paris, you have to check out the historic theater! Such a hidden gem.",
        "likes": 26206,
        "views": 6658422
    },
    {
        "id": 1322,
        "username": "yedwards",
        "email": "katelyntaylor@example.org",
        "createdOn": "01/29/2024 23:03:20",
        "comment": "Just tried the new dish at Chez Antoine. Definitely recommend the spaghetti carbonara if you love fresh flavors!",
        "likes": 25751,
        "views": 2778976
    },
    {
        "id": 1323,
        "username": "davislisa",
        "email": "powellmichael@example.net",
        "createdOn": "01/29/2024 10:51:08",
        "comment": "This year's Venice Biennale was the best yet! Loved every moment of the workshops, especially the part when world-renowned artists presented their works.",
        "likes": 39983,
        "views": 6589304
    },
    {
        "id": 1324,
        "username": "anthonymathis",
        "email": "millerbarbara@example.com",
        "createdOn": "01/29/2024 21:49:32",
        "comment": "My attempt at cooking ratatouille turned out delicious. Next time I'll adjust the baking time.",
        "likes": 19419,
        "views": 7644598
    },
    {
        "id": 1325,
        "username": "wflores",
        "email": "stacy25@example.com",
        "createdOn": "01/29/2024 19:34:11",
        "comment": "Had a lovely day at Central Park! The weather was perfect, and bird-watching was so relaxing.",
        "likes": 17223,
        "views": 9751822
    },
    {
        "id": 1326,
        "username": "franciscomorgan",
        "email": "tara56@example.net",
        "createdOn": "01/29/2024 19:34:57",
        "comment": "Exploring Japan was a dream come true! The scuba diving were out of this world.",
        "likes": 29644,
        "views": 252180
    },
    {
        "id": 1327,
        "username": "caitlin87",
        "email": "derek66@example.net",
        "createdOn": "01/29/2024 05:38:17",
        "comment": "My attempt at cooking lasagna turned out mediocre. Next time I'll use fresher ingredients.",
        "likes": 39348,
        "views": 8506866
    },
    {
        "id": 1328,
        "username": "bfreeman",
        "email": "madison33@example.com",
        "createdOn": "01/29/2024 16:40:33",
        "comment": "Can't stop listening to Drake's new album. God's Plan is my favorite track because it brings back memories.",
        "likes": 36577,
        "views": 3110028
    },
    {
        "id": 1329,
        "username": "raymond71",
        "email": "brownjoseph@example.org",
        "createdOn": "01/29/2024 18:36:22",
        "comment": "Today's workout was intense! Managed to beat my record at yoga session. Feeling exhausted!",
        "likes": 39891,
        "views": 6442742
    },
    {
        "id": 1330,
        "username": "brownlindsey",
        "email": "kstrickland@example.org",
        "createdOn": "01/29/2024 17:56:41",
        "comment": "Had a blast at sporting events in art gallery! The crowd was informative and the highlights were live performances.",
        "likes": 34630,
        "views": 2779893
    },
    {
        "id": 1331,
        "username": "russell32",
        "email": "twilliams@example.net",
        "createdOn": "01/29/2024 00:51:03",
        "comment": "Spent the weekend mountain biking at local river. Nature really is healing.",
        "likes": 35742,
        "views": 5350408
    },
    {
        "id": 1332,
        "username": "natalierodriguez",
        "email": "jchaney@example.org",
        "createdOn": "01/29/2024 22:23:20",
        "comment": "Can't believe what happened in the latest episode of The Mandalorian! Geralt of Rivia really surprised me.",
        "likes": 24219,
        "views": 6752481
    },
    {
        "id": 1333,
        "username": "thumphrey",
        "email": "benjaminsmith@example.com",
        "createdOn": "01/29/2024 02:01:56",
        "comment": "Can't stop listening to Taylor Swift's new album. Midnight Rain is my favorite track because it makes me want to dance.",
        "likes": 41738,
        "views": 7035188
    },
    {
        "id": 1334,
        "username": "haneybrad",
        "email": "smithjennifer@example.org",
        "createdOn": "01/29/2024 16:56:28",
        "comment": "My attempt at cooking pho turned out mediocre. Next time I'll try different spices.",
        "likes": 7225,
        "views": 8424075
    },
    {
        "id": 1335,
        "username": "philipbartlett",
        "email": "annettejones@example.com",
        "createdOn": "01/29/2024 12:11:26",
        "comment": "Feeling thoughtful after celebrating a milestone. Sometimes you just need to plan something fun.",
        "likes": 2416,
        "views": 6140497
    },
    {
        "id": 1336,
        "username": "leedanielle",
        "email": "ywatson@example.org",
        "createdOn": "01/29/2024 00:14:17",
        "comment": "Can't stop listening to Billie Eilish's new album. God's Plan is my favorite track because it brings back memories.",
        "likes": 24393,
        "views": 6081632
    },
    {
        "id": 1337,
        "username": "katherinethomas",
        "email": "tmitchell@example.com",
        "createdOn": "01/29/2024 02:24:36",
        "comment": "Can't believe what happened in the latest episode of Breaking Bad! Din Djarin really surprised me.",
        "likes": 6886,
        "views": 7752988
    }
]